{"commitInfo":{"timestamp":1733792454347,"operation":"CREATE TABLE","operationParameters":{"isManaged":"true","description":null,"partitionBy":"[]","properties":"{}"},"isolationLevel":"Serializable","isBlindAppend":true,"operationMetrics":{},"engineInfo":"Apache-Spark/3.3.2 Delta-Lake/2.3.0","txnId":"8dd1af96-ae6c-4e39-ab93-fc7cbf53cab8"}}
{"protocol":{"minReaderVersion":1,"minWriterVersion":2}}
{"metaData":{"id":"9dba1216-6102-4e9c-a474-4b787cdb68e8","format":{"provider":"parquet","options":{}},"schemaString":"{\"type\":\"struct\",\"fields\":[{\"name\":\"sid\",\"type\":\"string\",\"nullable\":true,\"metadata\":{}},{\"name\":\"id\",\"type\":\"string\",\"nullable\":true,\"metadata\":{}},{\"name\":\"position\",\"type\":\"string\",\"nullable\":true,\"metadata\":{}},{\"name\":\"created_at\",\"type\":\"string\",\"nullable\":true,\"metadata\":{}},{\"name\":\"created_meta\",\"type\":\"string\",\"nullable\":true,\"metadata\":{}},{\"name\":\"updated_at\",\"type\":\"string\",\"nullable\":true,\"metadata\":{}},{\"name\":\"updated_meta\",\"type\":\"string\",\"nullable\":true,\"metadata\":{}},{\"name\":\"meta\",\"type\":\"string\",\"nullable\":true,\"metadata\":{}},{\"name\":\"VIN_1_10\",\"type\":\"string\",\"nullable\":true,\"metadata\":{}},{\"name\":\"County\",\"type\":\"string\",\"nullable\":true,\"metadata\":{}},{\"name\":\"City\",\"type\":\"string\",\"nullable\":true,\"metadata\":{}},{\"name\":\"State\",\"type\":\"string\",\"nullable\":true,\"metadata\":{}},{\"name\":\"Postal_Code\",\"type\":\"string\",\"nullable\":true,\"metadata\":{}},{\"name\":\"Model_Year\",\"type\":\"string\",\"nullable\":true,\"metadata\":{}},{\"name\":\"Make\",\"type\":\"string\",\"nullable\":true,\"metadata\":{}},{\"name\":\"Model\",\"type\":\"string\",\"nullable\":true,\"metadata\":{}},{\"name\":\"Electric_Vehicle_Type\",\"type\":\"string\",\"nullable\":true,\"metadata\":{}},{\"name\":\"Clean_Alternative_Fuel_Vehicle_CAFV_Eligibility\",\"type\":\"string\",\"nullable\":true,\"metadata\":{}},{\"name\":\"Electric_Range\",\"type\":\"double\",\"nullable\":true,\"metadata\":{}},{\"name\":\"Base_MSRP\",\"type\":\"double\",\"nullable\":true,\"metadata\":{}},{\"name\":\"Legislative_District\",\"type\":\"double\",\"nullable\":true,\"metadata\":{}},{\"name\":\"DOL_Vehicle_ID\",\"type\":\"string\",\"nullable\":true,\"metadata\":{}},{\"name\":\"Vehicle_Location\",\"type\":\"string\",\"nullable\":true,\"metadata\":{}},{\"name\":\"Electric_Utility\",\"type\":\"string\",\"nullable\":true,\"metadata\":{}},{\"name\":\"2020_Census_Tract\",\"type\":\"string\",\"nullable\":true,\"metadata\":{}},{\"name\":\"Counties\",\"type\":\"double\",\"nullable\":true,\"metadata\":{}},{\"name\":\"Congressional_Districts\",\"type\":\"double\",\"nullable\":true,\"metadata\":{}},{\"name\":\"WAOFM_GIS_Legislative_District_Boundary\",\"type\":\"double\",\"nullable\":true,\"metadata\":{}}]}","partitionColumns":[],"configuration":{},"createdTime":1733792454336}}
