{"commitInfo":{"timestamp":1733792485293,"operation":"WRITE","operationParameters":{"mode":"Append","partitionBy":"[]"},"readVersion":4,"isolationLevel":"Serializable","isBlindAppend":true,"operationMetrics":{"numFiles":"2","numOutputRows":"1","numOutputBytes":"2237"},"engineInfo":"Apache-Spark/3.3.2 Delta-Lake/2.3.0","txnId":"aeac9700-9372-465e-ae4a-dbbf939139ee"}}
{"add":{"path":"part-00011-738aa341-f6fc-4fb8-b9a8-0ded452f720e-c000.snappy.parquet","partitionValues":{},"size":1562,"modificationTime":1733792485279,"dataChange":true,"stats":"{\"numRecords\":1,\"minValues\":{\"Table_Name\":\"EV_Data\",\"Progress\":\"Ingest_Gold\",\"Status\":\"In_Progress\",\"Start_time\":\"2024-12-10T01:01:25.144Z\"},\"maxValues\":{\"Table_Name\":\"EV_Data\",\"Progress\":\"Ingest_Gold\",\"Status\":\"In_Progress\",\"Start_time\":\"2024-12-10T01:01:25.144Z\"},\"nullCount\":{\"Table_Name\":0,\"Progress\":0,\"Status\":0,\"Start_time\":0,\"End_time\":1}}"}}
